cassyy/__init__.py
cassyy/core.py
cassyy/py.typed
cassyy-0.0.9.dist-info/licenses/LICENSE
cassyy-0.0.9.dist-info/WHEEL
cassyy-0.0.9.dist-info/METADATA
cassyy-0.0.9.dist-info/RECORD
