Metadata-Version: 2.4
Name: cassyy
Version: 0.0.9
Summary: Simple Apereo Central Authentication Service (CAS) client
Keywords: Authentication,SSO,CAS
Author-email: John Wagenleitner <johnwa@mail.fresnostate.edu>
Requires-Python: >=3.11
Classifier: Development Status :: 4 - Beta
Classifier: License :: OSI Approved :: Apache Software License
Classifier: Intended Audience :: Developers
License-File: LICENSE
Project-URL: Home, https://github.com/jowage58/cassyy
Project-URL: Source, https://github.com/jowage58/cassyy
